teslacam/VERSION
teslacam/__init__.py
teslacam/__main__.py
teslacam/config.py
teslacam/consts.py
teslacam/contracts.py
teslacam/enums.py
teslacam/funcs.py
teslacam/log.py
teslacam/models.py
teslacam/notifiers/__init__.py
teslacam/notifiers/pushover.py
teslacam/services/__init__.py
teslacam/services/filesystem.py
teslacam/services/notification.py
teslacam/services/upload.py
teslacam/services/web.py
teslacam/uploaders/__init__.py
teslacam/uploaders/blobstorage.py
teslacam/uploaders/filesystem.py
teslacam_py-20.9.2.dist-info/METADATA
teslacam_py-20.9.2.dist-info/WHEEL
teslacam_py-20.9.2.dist-info/entry_points.txt
teslacam_py-20.9.2.dist-info/top_level.txt
teslacam_py-20.9.2.dist-info/RECORD
